cloudsen12_models/cloudsen12.py
cloudsen12_models/utils_torch.py
cloudsen12_models-1.0.1.dist-info/LICENSE
cloudsen12_models-1.0.1.dist-info/METADATA
cloudsen12_models-1.0.1.dist-info/WHEEL
cloudsen12_models-1.0.1.dist-info/RECORD
