Metadata-Version: 2.1
Name: cloudsen12_models
Version: 1.0.1
Summary: 🛰️ CloudSEN12 models
Home-page: https://github.com/IPL-UV/cloudsen12_models
License: 	LGPL-3.0
Author: Gonzalo Mateo-García
Requires-Python: >=3.10,<4.0
Classifier: License :: Other/Proprietary License
Classifier: Programming Language :: Python :: 3
Classifier: Programming Language :: Python :: 3.10
Classifier: Programming Language :: Python :: 3.11
Classifier: Programming Language :: Python :: 3.12
Classifier: Programming Language :: Python :: 3.13
Requires-Dist: georeader-spaceml (>=1.4)
Requires-Dist: huggingface-hub (>=0.25)
Requires-Dist: numpy (>=1)
Requires-Dist: rasterio (>=1)
Requires-Dist: requests (>=2)
Requires-Dist: segmentation-models-pytorch (>=0.3)
Requires-Dist: torch (>=2)
Requires-Dist: tqdm (>=4)
Project-URL: Documentation, https://IPL-UV.github.io/cloudsen12_models/
Project-URL: Repository, https://github.com/IPL-UV/cloudsen12_models
